semantic_chunkers/__init__.py
semantic_chunkers/schema.py
semantic_chunkers/chunkers/__init__.py
semantic_chunkers/chunkers/base.py
semantic_chunkers/chunkers/consecutive.py
semantic_chunkers/chunkers/cumulative.py
semantic_chunkers/chunkers/regex.py
semantic_chunkers/chunkers/statistical.py
semantic_chunkers/splitters/__init__.py
semantic_chunkers/splitters/base.py
semantic_chunkers/splitters/regex.py
semantic_chunkers/utils/__init__.py
semantic_chunkers/utils/logger.py
semantic_chunkers/utils/text.py
semantic_chunkers-0.1.0.dist-info/METADATA
semantic_chunkers-0.1.0.dist-info/WHEEL
semantic_chunkers-0.1.0.dist-info/licenses/LICENSE
semantic_chunkers-0.1.0.dist-info/RECORD
