Metadata-Version: 2.4
Name: semantic-chunkers
Version: 0.1.0
Summary: Super advanced chunking methods for AI
Author-email: Aurelio AI <hello@aurelio.ai>
License: MIT License
License-File: LICENSE
Requires-Python: <3.14,>=3.10
Requires-Dist: colorama>=0.4.6
Requires-Dist: colorlog>=6.8.0
Requires-Dist: numpy>=1.26.0
Requires-Dist: pydantic>=2.5.3
Requires-Dist: regex>=2023.12.25
Requires-Dist: semantic-router>=0.1.0
Requires-Dist: tiktoken<1.0.0,>=0.7.0
Provides-Extra: dev
Requires-Dist: ipykernel<7,>=6.25.0; extra == 'dev'
Requires-Dist: mypy<2,>=1.7.1; extra == 'dev'
Requires-Dist: pytest-asyncio<0.25,>=0.24.0; extra == 'dev'
Requires-Dist: pytest-cov<5,>=4.1.0; extra == 'dev'
Requires-Dist: pytest-mock<4,>=3.12.0; extra == 'dev'
Requires-Dist: pytest-xdist<4,>=3.5.0; extra == 'dev'
Requires-Dist: pytest~=8.2; extra == 'dev'
Requires-Dist: requests-mock<2,>=1.12.1; extra == 'dev'
Requires-Dist: ruff<0.12,>=0.11.2; extra == 'dev'
Requires-Dist: types-pyyaml<7,>=6.0.12.12; extra == 'dev'
Requires-Dist: types-requests<3,>=2.31.0; extra == 'dev'
Provides-Extra: stats
Requires-Dist: matplotlib>=3.8.3; extra == 'stats'
